setup.cfg
setup.py
lad/__init__.py
lad/lad.py
lad.egg-info/PKG-INFO
lad.egg-info/SOURCES.txt
lad.egg-info/dependency_links.txt
lad.egg-info/requires.txt
lad.egg-info/top_level.txt